spycoprobe/__init__.py
spycoprobe/cli.py
spycoprobe/intelhex.py
spycoprobe/protocol.py
spycoprobe/spycoprobe.py
spycoprobe-1.0.6.dist-info/entry_points.txt
spycoprobe-1.0.6.dist-info/LICENSE.txt
spycoprobe-1.0.6.dist-info/WHEEL
spycoprobe-1.0.6.dist-info/METADATA
spycoprobe-1.0.6.dist-info/RECORD
